CHANGELOG.md
alembic_enums/__init__.py
alembic_enums/enum_migration.py
alembic_enums-0.4.1.dist-info/LICENSE
alembic_enums-0.4.1.dist-info/METADATA
alembic_enums-0.4.1.dist-info/WHEEL
alembic_enums-0.4.1.dist-info/RECORD
