Metadata-Version: 2.1
Name: alembic-enums
Version: 0.4.1
Summary: Support for migrating PostgreSQL enums with Alembic
Home-page: https://github.com/imankulov/alembic-enums
License: MIT
Author: Roman Imankulov
Author-email: roman.imankulov@gmail.com
Requires-Python: >=3.8,<4.0
Classifier: Intended Audience :: Developers
Classifier: License :: OSI Approved :: MIT License
Classifier: Programming Language :: Python :: 3
Classifier: Programming Language :: Python :: 3.8
Classifier: Programming Language :: Python :: 3.9
Classifier: Programming Language :: Python :: 3.10
Classifier: Programming Language :: Python :: 3.11
Project-URL: Repository, https://github.com/imankulov/alembic-enums
